porkyddns/main.py
porkyddns/utils.py
porkyddns-0.1.1.dist-info/entry_points.txt
porkyddns-0.1.1.dist-info/LICENSE
porkyddns-0.1.1.dist-info/METADATA
porkyddns-0.1.1.dist-info/WHEEL
porkyddns-0.1.1.dist-info/RECORD
