Metadata-Version: 2.1
Name: porkyddns
Version: 0.1.1
Summary: Simple Porkbun DDNS Client
License: GPLv3
Author: Michal S.
Author-email: mchal_@tuta.io
Requires-Python: >=3.9,<4.0
Classifier: License :: Other/Proprietary License
Classifier: Programming Language :: Python :: 3
Classifier: Programming Language :: Python :: 3.9
Classifier: Programming Language :: Python :: 3.10
Classifier: Programming Language :: Python :: 3.11
Requires-Dist: requests (>=2.28.2,<3.0.0)
Requires-Dist: toml (>=0.10.2,<0.11.0)
Requires-Dist: typer (>=0.7.0,<0.8.0)
Requires-Dist: urllib3 (>=1.26.14,<2.0.0)
